fastapi_rich_panels/__init__.py
fastapi_rich_panels/formatters.py
fastapi_rich_panels/middleware.py
fastapi_rich_panels/py.typed
fastapi_rich_panels-0.2.1.dist-info/LICENSE
fastapi_rich_panels-0.2.1.dist-info/METADATA
fastapi_rich_panels-0.2.1.dist-info/WHEEL
fastapi_rich_panels-0.2.1.dist-info/RECORD
