Metadata-Version: 2.3
Name: fastapi-rich-panels
Version: 0.2.1
Summary: Beautiful FastAPI request/response logging middleware with Rich panels
License: MIT
Author: danish903
Author-email: adhungel@ucdavis.edu
Requires-Python: >=3.9
Classifier: License :: OSI Approved :: MIT License
Classifier: Programming Language :: Python :: 3
Classifier: Programming Language :: Python :: 3.9
Classifier: Programming Language :: Python :: 3.10
Classifier: Programming Language :: Python :: 3.11
Classifier: Programming Language :: Python :: 3.12
Classifier: Programming Language :: Python :: 3.13
Requires-Dist: fastapi (>=0.116.1,<0.117.0)
Requires-Dist: rich (>=14.1.0,<15.0.0)
